edc_sync/__init__.py
edc_sync/settings.py
edc_sync/transaction_producer.py
edc_sync/classes/__init__.py
edc_sync/classes/consumer.py
edc_sync/exceptions/__init__.py
edc_sync/managers/__init__.py
edc_sync/managers/incoming_transaction_manager.py
edc_sync/mixins/__init__.py
edc_sync/mixins/sync_mixin.py
edc_sync/mixins/transaction_mixin.py
edc_sync/models/__init__.py
edc_sync/models/base_sync_uuid_model.py
edc_sync/models/base_transaction.py
edc_sync/models/consumer.py
edc_sync/models/incoming_transaction.py
edc_sync/models/middle_man_transaction.py
edc_sync/models/outgoing_transaction.py
edc_sync/models/producer.py
edc_sync/models/request_log.py
edc_sync/models/signals.py
edc_sync/models/sync_import_history_model.py
edc_sync/models/sync_lock_model.py
edc_sync/tests/__init__.py
edc_sync/tests/models.py
edc_sync/tests/test_tx.py
edc_sync-0.1.0a1.dist-info/DESCRIPTION.rst
edc_sync-0.1.0a1.dist-info/METADATA
edc_sync-0.1.0a1.dist-info/metadata.json
edc_sync-0.1.0a1.dist-info/RECORD
edc_sync-0.1.0a1.dist-info/top_level.txt
edc_sync-0.1.0a1.dist-info/WHEEL
