Metadata-Version: 2.0
Name: edc-sync
Version: 0.1.0a1
Summary: Sync models instances between client and server.
Home-page: https://github.com/botswana-harvard/edc-sync
Author: Erik van Widenfelt
Author-email: ew2789@gmail.com
License: GPL license, see LICENSE
Keywords: django data synchronization offline
Platform: UNKNOWN
Classifier: Environment :: Web Environment
Classifier: Framework :: Django
Classifier: Intended Audience :: Developers
Classifier: License :: OSI Approved :: GNU General Public License (GPL)
Classifier: Operating System :: OS Independent
Classifier: Programming Language :: Python
Classifier: Programming Language :: Python :: 3.4
Classifier: Topic :: Security :: Cryptography
Classifier: Topic :: Internet :: WWW/HTTP
Classifier: Topic :: Internet :: WWW/HTTP :: Dynamic Content
Requires-Dist: Django (>=1.7)
Requires-Dist: unipath (>=1.1)
Requires-Dist: django-crypto-fields (>=0.1)
Requires-Dist: edc-base (>=0.1)
